alertemail/__init__.py
alertemail/alertemail.py
csv/__init__.py
csv/getcsv.py
csv/getpotatocsv.py
potatocsv/getpotatocsv.py
potatoscript/__init__.py
potatoscript/alertemail.py
potatoscript/emailalert.py
sck/__init__.py
sck/emailalert.py
getpotatocsv-1.0.1.dist-info/METADATA
getpotatocsv-1.0.1.dist-info/WHEEL
getpotatocsv-1.0.1.dist-info/top_level.txt
getpotatocsv-1.0.1.dist-info/RECORD
